fourcats_flask/__init__.py
fourcats_flask/pluins/__init__.py
fourcats_flask/pluins/excepts.py
fourcats_flask/pluins/global_logger.py
fourcats_flask/pluins/token.py
fourcats_flask/refactor/__init__.py
fourcats_flask/refactor/api.py
fourcats_flask/refactor/app.py
fourcats_flask/refactor/argument.py
fourcats_flask/refactor/http_code.py
fourcats_flask/refactor/request_parser.py
fourcats_flask/refactor/requester.py
fourcats_flask/refactor/response.py
fourcats_flask/refactor/sqlalchemy.py
tests/__init__.py
tests/test_app.py
fourcats_flask-0.2.1.dist-info/LICENSE
fourcats_flask-0.2.1.dist-info/METADATA
fourcats_flask-0.2.1.dist-info/WHEEL
fourcats_flask-0.2.1.dist-info/top_level.txt
fourcats_flask-0.2.1.dist-info/RECORD
