Metadata-Version: 2.1
Name: fourcats-flask
Version: 0.2.1
Summary: A flask encapsulated based on personal habits for fast use.
Home-page: https://github.com/FourCats-Py/FourCats-Flask
Download-URL: https://github.com/FourCats-Py/FourCats-Flask/archive/0.2.1.tar.gz
Author: ShiWeiDong
Author-email: shiweidong1993@gmail.com
Keywords: fourcats,flask
Requires-Python: >=3.8
License-File: LICENSE
Requires-Dist: flask-restx >=1.2.0
Requires-Dist: Flask >=2.3.0
Requires-Dist: loguru >=0.6.0
Requires-Dist: PyYAML >=6.0
Requires-Dist: Flask-HTTPAuth >=4.7.0
Requires-Dist: mergedict >=1.0.0
Requires-Dist: urllib3 >=1.26.10
Requires-Dist: SQLAlchemy >=2.0.0
Requires-Dist: Flask-SQLAlchemy >=3.0.0
Requires-Dist: Flask-Cors >=3.0.10
Requires-Dist: PyJWT >=2.4.0
Requires-Dist: fourcats-utils >=0.0.4
Requires-Dist: six
Requires-Dist: certifi
